{
  "type": "grid",
  "data": {
    "columns": 32,
    "rowHeight": 28,
    "maxWidth": 1400,
    "bordered": true,
    "cells": [
      {
        "position": [
          0,
          0,
          27,
          2
        ]
      },
      {
        "position": [
          0,
          4,
          15,
          6
        ]
      },
      {
        "position": [
          0,
          11,
          14,
          14
        ]
      },
      {
        "position": [
          18,
          4,
          10,
          2
        ]
      },
      {
        "position": [
          19,
          6,
          8,
          3
        ]
      },
      {
        "position": [
          14,
          10,
          18,
          19
        ],
        "side": "left"
      },
      {
        "position": null
      },
      {
        "position": null
      },
      {
        "position": null
      },
      {
        "position": null
      },
      {
        "position": null
      },
      {
        "position": null
      },
      {
        "position": null
      },
      {
        "position": [
          0,
          31,
          6,
          3
        ]
      },
      {
        "position": [
          0,
          40,
          7,
          2
        ]
      },
      {
        "position": [
          0,
          29,
          11,
          2
        ]
      },
      {
        "position": [
          11,
          29,
          21,
          18
        ]
      },
      {
        "position": [
          1,
          47,
          8,
          4
        ]
      },
      {
        "position": [
          10,
          47,
          22,
          22
        ]
      },
      {
        "position": null
      },
      {
        "position": null
      },
      {
        "position": null
      },
      {
        "position": null
      },
      {
        "position": null
      }
    ]
  }
}